{"frames": {"1": {"frame": {"x": 2, "y": 2, "w": 640, "h": 480}, "regpoint": {"x": 320, "y": 240}, "dirFile": "03.DXR", "dirName": "03b001v0", "dirNum": 33}, "21": {"frame": {"x": 2, "y": 484, "w": 640, "h": 480}, "regpoint": {"x": 320, "y": 240}, "dirFile": "03.DXR", "dirName": "03b001v0", "dirNum": 101}, "4": {"frame": {"x": 644, "y": 484, "w": 48, "h": 284}, "regpoint": {"x": 320, "y": 219}, "dirFile": "03.DXR", "dirName": "02", "dirNum": 36}, "5": {"frame": {"x": 644, "y": 770, "w": 47, "h": 220}, "regpoint": {"x": 320, "y": 220}, "dirFile": "03.DXR", "dirName": "open2", "dirNum": 37}, "6": {"frame": {"x": 693, "y": 770, "w": 30, "h": 192}, "regpoint": {"x": 250, "y": 215}, "dirFile": "03.DXR", "dirName": "02", "dirNum": 38}, "2": {"frame": {"x": 725, "y": 2, "w": 94, "h": 154}, "regpoint": {"x": -154, "y": 228}, "dirFile": "03.DXR", "dirName": "02", "dirNum": 34}, "3": {"frame": {"x": 644, "y": 2, "w": 35, "h": 150}, "regpoint": {"x": -212, "y": 228}, "dirFile": "03.DXR", "dirName": "open1", "dirNum": 35}, "7": {"frame": {"x": 694, "y": 2, "w": 29, "h": 149}, "regpoint": {"x": 251, "y": 213}, "dirFile": "03.DXR", "dirName": "open3", "dirNum": 39}, "10": {"frame": {"x": 694, "y": 153, "w": 20, "h": 113}, "regpoint": {"x": -154, "y": 218}, "dirFile": "03.DXR", "dirName": "03", "dirNum": 83}, "12": {"frame": {"x": 644, "y": 154, "w": 30, "h": 113}, "regpoint": {"x": -153, "y": 220}, "dirFile": "03.DXR", "dirName": "05", "dirNum": 85}, "13": {"frame": {"x": 644, "y": 154, "w": 30, "h": 113}, "regpoint": {"x": -153, "y": 220}, "dirFile": "03.DXR", "dirName": "01", "dirNum": 86}, "14": {"frame": {"x": 644, "y": 269, "w": 30, "h": 113}, "regpoint": {"x": -153, "y": 220}, "dirFile": "03.DXR", "dirName": "02", "dirNum": 87}, "15": {"frame": {"x": 676, "y": 269, "w": 30, "h": 113}, "regpoint": {"x": -153, "y": 220}, "dirFile": "03.DXR", "dirName": "03", "dirNum": 88}, "16": {"frame": {"x": 821, "y": 2, "w": 30, "h": 113}, "regpoint": {"x": -153, "y": 220}, "dirFile": "03.DXR", "dirName": "04", "dirNum": 89}, "17": {"frame": {"x": 853, "y": 2, "w": 30, "h": 113}, "regpoint": {"x": -153, "y": 220}, "dirFile": "03.DXR", "dirName": "05", "dirNum": 90}, "18": {"frame": {"x": 885, "y": 2, "w": 30, "h": 113}, "regpoint": {"x": -153, "y": 220}, "dirFile": "03.DXR", "dirName": "06", "dirNum": 91}, "19": {"frame": {"x": 917, "y": 2, "w": 30, "h": 113}, "regpoint": {"x": -153, "y": 220}, "dirFile": "03.DXR", "dirName": "07", "dirNum": 92}, "20": {"frame": {"x": 949, "y": 2, "w": 30, "h": 113}, "regpoint": {"x": -153, "y": 220}, "dirFile": "03.DXR", "dirName": "08", "dirNum": 93}, "11": {"frame": {"x": 981, "y": 2, "w": 29, "h": 112}, "regpoint": {"x": -153, "y": 219}, "dirFile": "03.DXR", "dirName": "04", "dirNum": 84}, "9": {"frame": {"x": 676, "y": 154, "w": 14, "h": 87}, "regpoint": {"x": -154, "y": 217}, "dirFile": "03.DXR", "dirName": "02", "dirNum": 82}, "8": {"frame": {"x": 716, "y": 153, "w": 7, "h": 15}, "regpoint": {"x": -154, "y": 207}, "dirFile": "03.DXR", "dirName": "Figge_start", "dirNum": 81}}, "meta": {"size": {"w": 1024, "h": 1024}, "image": "assets/garage-sprites-0.png", "scale": "1"}}